gttk/__init__.py
gttk/gttk.tcl
gttk/libatk-1.0-0.dll
gttk/libbrotlicommon.dll
gttk/libbrotlidec.dll
gttk/libbz2-1.dll
gttk/libcairo-2.dll
gttk/libcairo-gobject-2.dll
gttk/libdatrie-1.dll
gttk/libexpat-1.dll
gttk/libffi-7.dll
gttk/libfontconfig-1.dll
gttk/libfreetype-6.dll
gttk/libfribidi-0.dll
gttk/libgcc_s_seh-1.dll
gttk/libgdk-win32-2.0-0.dll
gttk/libgdk_pixbuf-2.0-0.dll
gttk/libgio-2.0-0.dll
gttk/libglib-2.0-0.dll
gttk/libgmodule-2.0-0.dll
gttk/libgobject-2.0-0.dll
gttk/libgraphite2.dll
gttk/libgtk-win32-2.0-0.dll
gttk/libgttk.dll
gttk/libharfbuzz-0.dll
gttk/libiconv-2.dll
gttk/libintl-8.dll
gttk/libjpeg-8.dll
gttk/liblzma-5.dll
gttk/libpango-1.0-0.dll
gttk/libpangocairo-1.0-0.dll
gttk/libpangoft2-1.0-0.dll
gttk/libpangowin32-1.0-0.dll
gttk/libpcre-1.dll
gttk/libpixman-1-0.dll
gttk/libpng16-16.dll
gttk/librsvg-2-2.dll
gttk/libstdc++-6.dll
gttk/libthai-0.dll
gttk/libtiff-5.dll
gttk/libwinpthread-1.dll
gttk/libxml2-2.dll
gttk/libzstd.dll
gttk/pkgIndex.tcl
gttk/zlib1.dll
gttk/lib/gdk-pixbuf-2.0/2.10.0/loaders.cache
gttk/lib/gdk-pixbuf-2.0/2.10.0/loaders/libpixbufloader-ani.dll
gttk/lib/gdk-pixbuf-2.0/2.10.0/loaders/libpixbufloader-bmp.dll
gttk/lib/gdk-pixbuf-2.0/2.10.0/loaders/libpixbufloader-gif.dll
gttk/lib/gdk-pixbuf-2.0/2.10.0/loaders/libpixbufloader-icns.dll
gttk/lib/gdk-pixbuf-2.0/2.10.0/loaders/libpixbufloader-ico.dll
gttk/lib/gdk-pixbuf-2.0/2.10.0/loaders/libpixbufloader-jpeg.dll
gttk/lib/gdk-pixbuf-2.0/2.10.0/loaders/libpixbufloader-png.dll
gttk/lib/gdk-pixbuf-2.0/2.10.0/loaders/libpixbufloader-pnm.dll
gttk/lib/gdk-pixbuf-2.0/2.10.0/loaders/libpixbufloader-qtif.dll
gttk/lib/gdk-pixbuf-2.0/2.10.0/loaders/libpixbufloader-svg.dll
gttk/lib/gdk-pixbuf-2.0/2.10.0/loaders/libpixbufloader-tga.dll
gttk/lib/gdk-pixbuf-2.0/2.10.0/loaders/libpixbufloader-tiff.dll
gttk/lib/gdk-pixbuf-2.0/2.10.0/loaders/libpixbufloader-xbm.dll
gttk/lib/gdk-pixbuf-2.0/2.10.0/loaders/libpixbufloader-xpm.dll
gttk/lib/gtk-2.0/2.10.0/engines/libpixmap.dll
gttk-0.6.1.dist-info/LICENSE.md
gttk-0.6.1.dist-info/METADATA
gttk-0.6.1.dist-info/WHEEL
gttk-0.6.1.dist-info/top_level.txt
gttk-0.6.1.dist-info/RECORD
