Metadata-Version: 2.1
Name: gttk
Version: 0.6.1
Summary: GTK theme for Tkinter/ttk
Home-page: https://github.com/RedFantom/python-gttk
Author: The gttk/tile-gtk/gttk authors
License: GNU GPLv3
Download-URL: https://github.com/RedFantom/python-gttk/releases
Platform: UNKNOWN
